groq_agent/__init__.py
groq_agent/agentic_chat.py
groq_agent/agentic_system.py
groq_agent/api_client.py
groq_agent/chat_session.py
groq_agent/cli.py
groq_agent/config.py
groq_agent/diff_manager.py
groq_agent/enhanced_chat.py
groq_agent/file_operations.py
groq_agent/intelligent_agent.py
groq_agent/model_selector.py
tests/__init__.py
tests/test_config.py
codeflow_cli-0.1.3.dist-info/METADATA
codeflow_cli-0.1.3.dist-info/WHEEL
codeflow_cli-0.1.3.dist-info/entry_points.txt
codeflow_cli-0.1.3.dist-info/top_level.txt
codeflow_cli-0.1.3.dist-info/RECORD
