Metadata-Version: 2.1
Name: codeflow-cli
Version: 0.1.3
Summary: Advanced AI coding assistant with Cursor AI-style agentic capabilities, semantic search, and intelligent code operations
Home-page: https://github.com/your-username/codeflow-cli
Author: Groq CLI Team
Author-email: TM NABEEL <tmnabeel30@example.com>
License: MIT
Keywords: ai,coding,assistant,cursor,agentic,semantic-search,code-analysis,terminal,cli,groq,llm,developer-tools
Classifier: Development Status :: 4 - Beta
Classifier: Intended Audience :: Developers
Classifier: Topic :: Software Development :: Debuggers
Classifier: Topic :: Software Development :: Quality Assurance
Classifier: Topic :: Software Development :: Code Generators
Classifier: Topic :: Text Processing :: Linguistic
Classifier: Programming Language :: Python :: 3
Classifier: Programming Language :: Python :: 3.8
Classifier: Programming Language :: Python :: 3.9
Classifier: Programming Language :: Python :: 3.10
Classifier: Programming Language :: Python :: 3.11
Classifier: Programming Language :: Python :: 3.12
Classifier: Environment :: Console
Classifier: Operating System :: OS Independent
Requires-Python: >=3.8
Requires-Dist: groq (>=0.4.0)
Requires-Dist: click (>=8.0.0)
Requires-Dist: rich (>=13.0.0)
Requires-Dist: prompt-toolkit (>=3.0.0)
Requires-Dist: pyyaml (>=6.0)
Requires-Dist: colorama (>=0.4.6)
Requires-Dist: typer (>=0.9.0)
Provides-Extra: dev
Requires-Dist: pytest (>=7.0.0) ; extra == 'dev'
Requires-Dist: black (>=23.0.0) ; extra == 'dev'
Requires-Dist: flake8 (>=6.0.0) ; extra == 'dev'
Requires-Dist: mypy (>=1.0.0) ; extra == 'dev'
